robotaxi/__init__.py
robotaxi/module.py
text2video/__init__.py
text2video/module.py
robotaxi-0.0.1.dist-info/METADATA
robotaxi-0.0.1.dist-info/WHEEL
robotaxi-0.0.1.dist-info/top_level.txt
robotaxi-0.0.1.dist-info/RECORD
